tripawnOpen/__init__.py
tripawnOpen/operation.py
tripawnOpen-0.1.9.dist-info/METADATA
tripawnOpen-0.1.9.dist-info/WHEEL
tripawnOpen-0.1.9.dist-info/top_level.txt
tripawnOpen-0.1.9.dist-info/RECORD
